{"data":[[{"x":76,"y":501,"color":"red","lineWidth":2},{"x":77,"y":501,"color":"red","lineWidth":2},{"x":79,"y":502,"color":"red","lineWidth":2},{"x":81,"y":505,"color":"red","lineWidth":2},{"x":87,"y":509,"color":"red","lineWidth":2},{"x":93,"y":513,"color":"red","lineWidth":2},{"x":99,"y":517,"color":"red","lineWidth":2},{"x":102,"y":520,"color":"red","lineWidth":2},{"x":103,"y":521,"color":"red","lineWidth":2},{"x":104,"y":521,"color":"red","lineWidth":2},{"x":104,"y":522,"color":"red","lineWidth":2},{"x":106,"y":524,"color":"red","lineWidth":2},{"x":107,"y":525,"color":"red","lineWidth":2},{"x":108,"y":525,"color":"red","lineWidth":2},{"x":110,"y":522,"color":"red","lineWidth":2},{"x":112,"y":519,"color":"red","lineWidth":2},{"x":115,"y":515,"color":"red","lineWidth":2},{"x":119,"y":510,"color":"red","lineWidth":2},{"x":119,"y":508,"color":"red","lineWidth":2},{"x":120,"y":506,"color":"red","lineWidth":2},{"x":121,"y":503,"color":"red","lineWidth":2},{"x":123,"y":501,"color":"red","lineWidth":2},{"x":124,"y":498,"color":"red","lineWidth":2},{"x":126,"y":494,"color":"red","lineWidth":2},{"x":128,"y":491,"color":"red","lineWidth":2},{"x":131,"y":486,"color":"red","lineWidth":2},{"x":131,"y":484,"color":"red","lineWidth":2},{"x":132,"y":482,"color":"red","lineWidth":2},{"x":134,"y":481,"color":"red","lineWidth":2},{"x":135,"y":479,"color":"red","lineWidth":2},{"x":137,"y":477,"color":"red","lineWidth":2},{"x":139,"y":475,"color":"red","lineWidth":2},{"x":140,"y":473,"color":"red","lineWidth":2},{"x":141,"y":472,"color":"red","lineWidth":2},{"x":142,"y":471,"color":"red","lineWidth":2},{"x":143,"y":469,"color":"red","lineWidth":2},{"x":145,"y":468,"color":"red","lineWidth":2},{"x":146,"y":466,"color":"red","lineWidth":2},{"x":146,"y":465,"color":"red","lineWidth":2},{"x":147,"y":465,"color":"red","lineWidth":2}],[{"x":75,"y":1644,"color":"red","lineWidth":2},{"x":76,"y":1644,"color":"red","lineWidth":2},{"x":82,"y":1650,"color":"red","lineWidth":2},{"x":87,"y":1656,"color":"red","lineWidth":2},{"x":91,"y":1660,"color":"red","lineWidth":2},{"x":94,"y":1664,"color":"red","lineWidth":2},{"x":95,"y":1666,"color":"red","lineWidth":2},{"x":96,"y":1667,"color":"red","lineWidth":2},{"x":98,"y":1669,"color":"red","lineWidth":2},{"x":100,"y":1671,"color":"red","lineWidth":2},{"x":102,"y":1673,"color":"red","lineWidth":2},{"x":102,"y":1674,"color":"red","lineWidth":2},{"x":104,"y":1676,"color":"red","lineWidth":2},{"x":104,"y":1675,"color":"red","lineWidth":2},{"x":105,"y":1673,"color":"red","lineWidth":2},{"x":106,"y":1670,"color":"red","lineWidth":2},{"x":108,"y":1666,"color":"red","lineWidth":2},{"x":108,"y":1663,"color":"red","lineWidth":2},{"x":110,"y":1661,"color":"red","lineWidth":2},{"x":114,"y":1655,"color":"red","lineWidth":2},{"x":121,"y":1648,"color":"red","lineWidth":2},{"x":127,"y":1641,"color":"red","lineWidth":2},{"x":131,"y":1636,"color":"red","lineWidth":2},{"x":134,"y":1632,"color":"red","lineWidth":2},{"x":137,"y":1629,"color":"red","lineWidth":2},{"x":139,"y":1626,"color":"red","lineWidth":2},{"x":141,"y":1624,"color":"red","lineWidth":2},{"x":141,"y":1623,"color":"red","lineWidth":2},{"x":142,"y":1621,"color":"red","lineWidth":2},{"x":143,"y":1620,"color":"red","lineWidth":2},{"x":144,"y":1619,"color":"red","lineWidth":2},{"x":146,"y":1616,"color":"red","lineWidth":2},{"x":148,"y":1614,"color":"red","lineWidth":2},{"x":149,"y":1613,"color":"red","lineWidth":2},{"x":150,"y":1613,"color":"red","lineWidth":2},{"x":150,"y":1612,"color":"red","lineWidth":2},{"x":152,"y":1610,"color":"red","lineWidth":2},{"x":154,"y":1609,"color":"red","lineWidth":2},{"x":155,"y":1607,"color":"red","lineWidth":2},{"x":156,"y":1607,"color":"red","lineWidth":2}],[{"x":75,"y":2304,"color":"red","lineWidth":2},{"x":75,"y":2305,"color":"red","lineWidth":2},{"x":76,"y":2308,"color":"red","lineWidth":2},{"x":80,"y":2312,"color":"red","lineWidth":2},{"x":85,"y":2317,"color":"red","lineWidth":2},{"x":91,"y":2322,"color":"red","lineWidth":2},{"x":94,"y":2325,"color":"red","lineWidth":2},{"x":97,"y":2328,"color":"red","lineWidth":2},{"x":98,"y":2330,"color":"red","lineWidth":2},{"x":100,"y":2332,"color":"red","lineWidth":2},{"x":102,"y":2335,"color":"red","lineWidth":2},{"x":103,"y":2337,"color":"red","lineWidth":2},{"x":105,"y":2340,"color":"red","lineWidth":2},{"x":105,"y":2341,"color":"red","lineWidth":2},{"x":107,"y":2342,"color":"red","lineWidth":2},{"x":110,"y":2346,"color":"red","lineWidth":2},{"x":110,"y":2347,"color":"red","lineWidth":2}],[{"x":123,"y":2307,"color":"red","lineWidth":2},{"x":119,"y":2307,"color":"red","lineWidth":2},{"x":113,"y":2310,"color":"red","lineWidth":2},{"x":105,"y":2314,"color":"red","lineWidth":2},{"x":97,"y":2319,"color":"red","lineWidth":2},{"x":88,"y":2324,"color":"red","lineWidth":2},{"x":81,"y":2328,"color":"red","lineWidth":2},{"x":75,"y":2332,"color":"red","lineWidth":2},{"x":73,"y":2334,"color":"red","lineWidth":2},{"x":73,"y":2335,"color":"red","lineWidth":2},{"x":72,"y":2337,"color":"red","lineWidth":2},{"x":70,"y":2339,"color":"red","lineWidth":2},{"x":67,"y":2343,"color":"red","lineWidth":2},{"x":65,"y":2345,"color":"red","lineWidth":2},{"x":63,"y":2347,"color":"red","lineWidth":2},{"x":62,"y":2348,"color":"red","lineWidth":2},{"x":62,"y":2349,"color":"red","lineWidth":2}],[{"x":68,"y":3510,"color":"red","lineWidth":2},{"x":69,"y":3510,"color":"red","lineWidth":2},{"x":72,"y":3511,"color":"red","lineWidth":2},{"x":78,"y":3516,"color":"red","lineWidth":2},{"x":86,"y":3523,"color":"red","lineWidth":2},{"x":93,"y":3529,"color":"red","lineWidth":2},{"x":99,"y":3534,"color":"red","lineWidth":2},{"x":100,"y":3534,"color":"red","lineWidth":2},{"x":102,"y":3532,"color":"red","lineWidth":2},{"x":103,"y":3530,"color":"red","lineWidth":2},{"x":109,"y":3525,"color":"red","lineWidth":2},{"x":116,"y":3518,"color":"red","lineWidth":2},{"x":126,"y":3510,"color":"red","lineWidth":2},{"x":134,"y":3503,"color":"red","lineWidth":2},{"x":141,"y":3496,"color":"red","lineWidth":2},{"x":144,"y":3494,"color":"red","lineWidth":2},{"x":146,"y":3492,"color":"red","lineWidth":2},{"x":147,"y":3491,"color":"red","lineWidth":2},{"x":149,"y":3490,"color":"red","lineWidth":2},{"x":151,"y":3489,"color":"red","lineWidth":2},{"x":155,"y":3486,"color":"red","lineWidth":2},{"x":159,"y":3484,"color":"red","lineWidth":2},{"x":167,"y":3480,"color":"red","lineWidth":2},{"x":178,"y":3476,"color":"red","lineWidth":2},{"x":193,"y":3470,"color":"red","lineWidth":2},{"x":201,"y":3466,"color":"red","lineWidth":2},{"x":205,"y":3464,"color":"red","lineWidth":2},{"x":208,"y":3463,"color":"red","lineWidth":2},{"x":209,"y":3462,"color":"red","lineWidth":2},{"x":211,"y":3462,"color":"red","lineWidth":2},{"x":213,"y":3461,"color":"red","lineWidth":2}]],"frm":[[{"x":1177,"y":0,"color":"blue","lineWidth":3},{"x":1177,"y":6066}]],"meta":{"width":1182,"height":6066}}