{"data":[[{"x":71,"y":489,"color":"red","lineWidth":2},{"x":68,"y":489,"color":"red","lineWidth":2},{"x":68,"y":488,"color":"red","lineWidth":2},{"x":69,"y":489,"color":"red","lineWidth":2},{"x":75,"y":493,"color":"red","lineWidth":2},{"x":82,"y":500,"color":"red","lineWidth":2},{"x":83,"y":501,"color":"red","lineWidth":2},{"x":84,"y":501,"color":"red","lineWidth":2},{"x":88,"y":504,"color":"red","lineWidth":2},{"x":90,"y":506,"color":"red","lineWidth":2},{"x":91,"y":506,"color":"red","lineWidth":2},{"x":92,"y":505,"color":"red","lineWidth":2},{"x":92,"y":501,"color":"red","lineWidth":2},{"x":95,"y":496,"color":"red","lineWidth":2},{"x":98,"y":490,"color":"red","lineWidth":2},{"x":104,"y":483,"color":"red","lineWidth":2},{"x":108,"y":480,"color":"red","lineWidth":2},{"x":112,"y":476,"color":"red","lineWidth":2},{"x":119,"y":471,"color":"red","lineWidth":2},{"x":123,"y":468,"color":"red","lineWidth":2},{"x":127,"y":464,"color":"red","lineWidth":2},{"x":128,"y":461,"color":"red","lineWidth":2},{"x":130,"y":455,"color":"red","lineWidth":2},{"x":133,"y":451,"color":"red","lineWidth":2},{"x":137,"y":448,"color":"red","lineWidth":2},{"x":141,"y":446,"color":"red","lineWidth":2},{"x":144,"y":444,"color":"red","lineWidth":2},{"x":147,"y":442,"color":"red","lineWidth":2}],[{"x":81,"y":1467,"color":"red","lineWidth":2},{"x":78,"y":1466,"color":"red","lineWidth":2},{"x":76,"y":1465,"color":"red","lineWidth":2},{"x":73,"y":1465,"color":"red","lineWidth":2},{"x":72,"y":1465,"color":"red","lineWidth":2},{"x":72,"y":1464,"color":"red","lineWidth":2},{"x":75,"y":1466,"color":"red","lineWidth":2},{"x":80,"y":1470,"color":"red","lineWidth":2},{"x":87,"y":1475,"color":"red","lineWidth":2},{"x":89,"y":1477,"color":"red","lineWidth":2},{"x":90,"y":1477,"color":"red","lineWidth":2},{"x":91,"y":1478,"color":"red","lineWidth":2},{"x":92,"y":1479,"color":"red","lineWidth":2},{"x":95,"y":1481,"color":"red","lineWidth":2},{"x":96,"y":1481,"color":"red","lineWidth":2},{"x":97,"y":1482,"color":"red","lineWidth":2},{"x":98,"y":1482,"color":"red","lineWidth":2},{"x":98,"y":1481,"color":"red","lineWidth":2},{"x":102,"y":1474,"color":"red","lineWidth":2},{"x":109,"y":1466,"color":"red","lineWidth":2},{"x":115,"y":1454,"color":"red","lineWidth":2},{"x":117,"y":1450,"color":"red","lineWidth":2},{"x":121,"y":1444,"color":"red","lineWidth":2},{"x":126,"y":1439,"color":"red","lineWidth":2},{"x":132,"y":1432,"color":"red","lineWidth":2},{"x":136,"y":1427,"color":"red","lineWidth":2},{"x":138,"y":1424,"color":"red","lineWidth":2},{"x":142,"y":1418,"color":"red","lineWidth":2},{"x":144,"y":1415,"color":"red","lineWidth":2},{"x":145,"y":1415,"color":"red","lineWidth":2},{"x":145,"y":1414,"color":"red","lineWidth":2}],[{"x":75,"y":6268,"color":"red","lineWidth":2},{"x":75,"y":6267,"color":"red","lineWidth":2},{"x":75,"y":6268,"color":"red","lineWidth":2},{"x":77,"y":6269,"color":"red","lineWidth":2},{"x":79,"y":6272,"color":"red","lineWidth":2},{"x":81,"y":6276,"color":"red","lineWidth":2},{"x":82,"y":6278,"color":"red","lineWidth":2},{"x":84,"y":6280,"color":"red","lineWidth":2},{"x":87,"y":6282,"color":"red","lineWidth":2},{"x":88,"y":6284,"color":"red","lineWidth":2},{"x":91,"y":6287,"color":"red","lineWidth":2},{"x":93,"y":6289,"color":"red","lineWidth":2},{"x":98,"y":6291,"color":"red","lineWidth":2},{"x":101,"y":6293,"color":"red","lineWidth":2},{"x":105,"y":6295,"color":"red","lineWidth":2},{"x":109,"y":6296,"color":"red","lineWidth":2},{"x":113,"y":6298,"color":"red","lineWidth":2},{"x":115,"y":6301,"color":"red","lineWidth":2},{"x":117,"y":6302,"color":"red","lineWidth":2},{"x":117,"y":6303,"color":"red","lineWidth":2},{"x":118,"y":6304,"color":"red","lineWidth":2},{"x":119,"y":6306,"color":"red","lineWidth":2},{"x":120,"y":6306,"color":"red","lineWidth":2},{"x":121,"y":6306,"color":"red","lineWidth":2},{"x":116,"y":6304,"color":"red","lineWidth":2}],[{"x":54,"y":6305,"color":"red","lineWidth":2},{"x":55,"y":6305,"color":"red","lineWidth":2},{"x":58,"y":6305,"color":"red","lineWidth":2},{"x":66,"y":6301,"color":"red","lineWidth":2},{"x":79,"y":6296,"color":"red","lineWidth":2},{"x":86,"y":6292,"color":"red","lineWidth":2},{"x":95,"y":6287,"color":"red","lineWidth":2},{"x":98,"y":6284,"color":"red","lineWidth":2},{"x":100,"y":6282,"color":"red","lineWidth":2},{"x":104,"y":6279,"color":"red","lineWidth":2},{"x":109,"y":6277,"color":"red","lineWidth":2},{"x":115,"y":6272,"color":"red","lineWidth":2},{"x":121,"y":6268,"color":"red","lineWidth":2},{"x":125,"y":6265,"color":"red","lineWidth":2},{"x":128,"y":6262,"color":"red","lineWidth":2},{"x":129,"y":6262,"color":"red","lineWidth":2},{"x":129,"y":6261,"color":"red","lineWidth":2},{"x":128,"y":6261,"color":"red","lineWidth":2}],[{"x":60,"y":8795,"color":"red","lineWidth":2},{"x":62,"y":8795,"color":"red","lineWidth":2},{"x":63,"y":8795,"color":"red","lineWidth":2},{"x":64,"y":8795,"color":"red","lineWidth":2},{"x":65,"y":8797,"color":"red","lineWidth":2},{"x":67,"y":8799,"color":"red","lineWidth":2},{"x":68,"y":8801,"color":"red","lineWidth":2},{"x":69,"y":8805,"color":"red","lineWidth":2},{"x":71,"y":8807,"color":"red","lineWidth":2},{"x":74,"y":8809,"color":"red","lineWidth":2},{"x":77,"y":8810,"color":"red","lineWidth":2},{"x":80,"y":8811,"color":"red","lineWidth":2},{"x":82,"y":8813,"color":"red","lineWidth":2},{"x":84,"y":8815,"color":"red","lineWidth":2},{"x":86,"y":8816,"color":"red","lineWidth":2},{"x":86,"y":8817,"color":"red","lineWidth":2},{"x":88,"y":8817,"color":"red","lineWidth":2},{"x":89,"y":8818,"color":"red","lineWidth":2},{"x":92,"y":8819,"color":"red","lineWidth":2},{"x":93,"y":8820,"color":"red","lineWidth":2},{"x":94,"y":8821,"color":"red","lineWidth":2},{"x":94,"y":8822,"color":"red","lineWidth":2},{"x":95,"y":8822,"color":"red","lineWidth":2},{"x":96,"y":8822,"color":"red","lineWidth":2},{"x":96,"y":8819,"color":"red","lineWidth":2},{"x":99,"y":8816,"color":"red","lineWidth":2},{"x":103,"y":8810,"color":"red","lineWidth":2},{"x":110,"y":8802,"color":"red","lineWidth":2},{"x":113,"y":8796,"color":"red","lineWidth":2},{"x":117,"y":8791,"color":"red","lineWidth":2},{"x":123,"y":8784,"color":"red","lineWidth":2},{"x":127,"y":8778,"color":"red","lineWidth":2},{"x":132,"y":8772,"color":"red","lineWidth":2},{"x":135,"y":8767,"color":"red","lineWidth":2},{"x":141,"y":8761,"color":"red","lineWidth":2},{"x":146,"y":8757,"color":"red","lineWidth":2},{"x":150,"y":8752,"color":"red","lineWidth":2},{"x":154,"y":8747,"color":"red","lineWidth":2},{"x":155,"y":8746,"color":"red","lineWidth":2},{"x":155,"y":8747,"color":"red","lineWidth":2}],[{"x":76,"y":10317,"color":"red","lineWidth":2},{"x":78,"y":10316,"color":"red","lineWidth":2},{"x":79,"y":10316,"color":"red","lineWidth":2},{"x":79,"y":10317,"color":"red","lineWidth":2},{"x":80,"y":10318,"color":"red","lineWidth":2},{"x":83,"y":10322,"color":"red","lineWidth":2},{"x":87,"y":10326,"color":"red","lineWidth":2},{"x":91,"y":10330,"color":"red","lineWidth":2},{"x":94,"y":10333,"color":"red","lineWidth":2},{"x":97,"y":10335,"color":"red","lineWidth":2},{"x":100,"y":10338,"color":"red","lineWidth":2},{"x":102,"y":10341,"color":"red","lineWidth":2},{"x":105,"y":10343,"color":"red","lineWidth":2},{"x":108,"y":10347,"color":"red","lineWidth":2},{"x":111,"y":10349,"color":"red","lineWidth":2},{"x":116,"y":10351,"color":"red","lineWidth":2},{"x":118,"y":10352,"color":"red","lineWidth":2},{"x":119,"y":10352,"color":"red","lineWidth":2},{"x":120,"y":10353,"color":"red","lineWidth":2},{"x":121,"y":10355,"color":"red","lineWidth":2},{"x":122,"y":10355,"color":"red","lineWidth":2},{"x":122,"y":10354,"color":"red","lineWidth":2},{"x":122,"y":10353,"color":"red","lineWidth":2}],[{"x":120,"y":10312,"color":"red","lineWidth":2},{"x":119,"y":10312,"color":"red","lineWidth":2},{"x":118,"y":10313,"color":"red","lineWidth":2},{"x":117,"y":10314,"color":"red","lineWidth":2},{"x":113,"y":10318,"color":"red","lineWidth":2},{"x":107,"y":10322,"color":"red","lineWidth":2},{"x":101,"y":10325,"color":"red","lineWidth":2},{"x":94,"y":10329,"color":"red","lineWidth":2},{"x":88,"y":10331,"color":"red","lineWidth":2},{"x":85,"y":10334,"color":"red","lineWidth":2},{"x":78,"y":10337,"color":"red","lineWidth":2},{"x":74,"y":10340,"color":"red","lineWidth":2},{"x":71,"y":10341,"color":"red","lineWidth":2},{"x":68,"y":10344,"color":"red","lineWidth":2},{"x":65,"y":10346,"color":"red","lineWidth":2},{"x":61,"y":10349,"color":"red","lineWidth":2},{"x":57,"y":10351,"color":"red","lineWidth":2},{"x":53,"y":10354,"color":"red","lineWidth":2},{"x":51,"y":10355,"color":"red","lineWidth":2},{"x":50,"y":10356,"color":"red","lineWidth":2},{"x":51,"y":10356,"color":"red","lineWidth":2},{"x":52,"y":10356,"color":"red","lineWidth":2}],[{"x":90,"y":12600,"color":"red","lineWidth":2},{"x":89,"y":12600,"color":"red","lineWidth":2},{"x":87,"y":12600,"color":"red","lineWidth":2}],[{"x":90,"y":12600,"color":"red","lineWidth":2},{"x":84,"y":12600,"color":"red","lineWidth":2},{"x":83,"y":12600,"color":"red","lineWidth":2},{"x":83,"y":12599,"color":"red","lineWidth":2},{"x":82,"y":12599,"color":"red","lineWidth":2},{"x":83,"y":12599,"color":"red","lineWidth":2},{"x":88,"y":12603,"color":"red","lineWidth":2},{"x":95,"y":12609,"color":"red","lineWidth":2},{"x":98,"y":12612,"color":"red","lineWidth":2},{"x":101,"y":12615,"color":"red","lineWidth":2},{"x":105,"y":12619,"color":"red","lineWidth":2},{"x":109,"y":12621,"color":"red","lineWidth":2},{"x":112,"y":12624,"color":"red","lineWidth":2},{"x":114,"y":12625,"color":"red","lineWidth":2},{"x":117,"y":12627,"color":"red","lineWidth":2},{"x":118,"y":12628,"color":"red","lineWidth":2},{"x":120,"y":12629,"color":"red","lineWidth":2},{"x":122,"y":12630,"color":"red","lineWidth":2},{"x":123,"y":12631,"color":"red","lineWidth":2},{"x":124,"y":12631,"color":"red","lineWidth":2},{"x":124,"y":12629,"color":"red","lineWidth":2}],[{"x":116,"y":12596,"color":"red","lineWidth":2},{"x":116,"y":12597,"color":"red","lineWidth":2},{"x":115,"y":12598,"color":"red","lineWidth":2},{"x":111,"y":12601,"color":"red","lineWidth":2},{"x":102,"y":12608,"color":"red","lineWidth":2},{"x":96,"y":12612,"color":"red","lineWidth":2},{"x":91,"y":12617,"color":"red","lineWidth":2},{"x":88,"y":12620,"color":"red","lineWidth":2},{"x":85,"y":12622,"color":"red","lineWidth":2},{"x":80,"y":12627,"color":"red","lineWidth":2},{"x":77,"y":12629,"color":"red","lineWidth":2},{"x":73,"y":12632,"color":"red","lineWidth":2},{"x":71,"y":12634,"color":"red","lineWidth":2},{"x":63,"y":12639,"color":"red","lineWidth":2},{"x":58,"y":12642,"color":"red","lineWidth":2},{"x":56,"y":12644,"color":"red","lineWidth":2},{"x":56,"y":12643,"color":"red","lineWidth":2}],[{"x":76,"y":13613,"color":"red","lineWidth":2},{"x":78,"y":13612,"color":"red","lineWidth":2},{"x":79,"y":13612,"color":"red","lineWidth":2},{"x":83,"y":13614,"color":"red","lineWidth":2},{"x":87,"y":13617,"color":"red","lineWidth":2},{"x":93,"y":13622,"color":"red","lineWidth":2},{"x":101,"y":13627,"color":"red","lineWidth":2},{"x":104,"y":13629,"color":"red","lineWidth":2},{"x":108,"y":13633,"color":"red","lineWidth":2},{"x":110,"y":13635,"color":"red","lineWidth":2},{"x":110,"y":13636,"color":"red","lineWidth":2},{"x":111,"y":13638,"color":"red","lineWidth":2},{"x":112,"y":13638,"color":"red","lineWidth":2},{"x":113,"y":13638,"color":"red","lineWidth":2},{"x":114,"y":13637,"color":"red","lineWidth":2},{"x":117,"y":13629,"color":"red","lineWidth":2},{"x":123,"y":13612,"color":"red","lineWidth":2},{"x":129,"y":13603,"color":"red","lineWidth":2},{"x":134,"y":13595,"color":"red","lineWidth":2},{"x":135,"y":13590,"color":"red","lineWidth":2},{"x":136,"y":13587,"color":"red","lineWidth":2},{"x":138,"y":13584,"color":"red","lineWidth":2},{"x":140,"y":13581,"color":"red","lineWidth":2},{"x":144,"y":13575,"color":"red","lineWidth":2},{"x":147,"y":13568,"color":"red","lineWidth":2},{"x":150,"y":13563,"color":"red","lineWidth":2},{"x":153,"y":13560,"color":"red","lineWidth":2},{"x":153,"y":13559,"color":"red","lineWidth":2},{"x":153,"y":13558,"color":"red","lineWidth":2},{"x":155,"y":13557,"color":"red","lineWidth":2},{"x":159,"y":13553,"color":"red","lineWidth":2},{"x":160,"y":13552,"color":"red","lineWidth":2},{"x":160,"y":13550,"color":"red","lineWidth":2}]],"frm":[[{"x":1177,"y":0,"color":"blue","lineWidth":3},{"x":1177,"y":17789}]],"meta":{"width":1181,"height":17789}}